LICENSE
README.md
setup.cfg
setup.py
src/edenredpt/__init__.py
src/edenredpt/edenredpt.py
src/edenredpt/exceptions.py
src/edenredpt.egg-info/PKG-INFO
src/edenredpt.egg-info/SOURCES.txt
src/edenredpt.egg-info/dependency_links.txt
src/edenredpt.egg-info/requires.txt
src/edenredpt.egg-info/top_level.txt