Metadata-Version: 2.1
Name: edenredpt
Version: 0.1.2
Summary: Unofficial library for myEdenred (PT)
Home-page: https://github.com/joaoduartemiranda/edenredpt
Author: João Miranda
Author-email: joao.duarte.miranda@gmail.com
License: UNKNOWN
Platform: UNKNOWN
License-File: LICENSE
